twixfact/__init__.py
twixfact/fact.py
twixfact-0.0.4.dist-info/METADATA
twixfact-0.0.4.dist-info/WHEEL
twixfact-0.0.4.dist-info/top_level.txt
twixfact-0.0.4.dist-info/RECORD
