Metadata-Version: 2.1
Name: twixfact
Version: 0.0.4
Summary: Factorial Package
Home-page: UNKNOWN
Author: twixour (Raushan Kashyap)
Author-email: <twixour@gmail.com>
License: UNKNOWN
Keywords: python,factorial
Platform: UNKNOWN
Classifier: Development Status :: 1 - Planning
Classifier: Intended Audience :: Developers
Classifier: Programming Language :: Python :: 3
Classifier: Operating System :: Unix
Classifier: Operating System :: MacOS :: MacOS X
Classifier: Operating System :: Microsoft :: Windows
